nurse/__init__.py
nurse/api.py
nurse/exceptions.py
nurse/service_catalog.py
nurse-0.5.1.dist-info/METADATA
nurse-0.5.1.dist-info/WHEEL
nurse-0.5.1.dist-info/RECORD
