Metadata-Version: 2.1
Name: nurse
Version: 0.5.1
Summary: A thoughtful dependency injection framework 💉
Home-page: https://github.com/ZeroGachis/nurse
Keywords: dependency,injection
Author: ducdetronquito
Author-email: g.paulet@zero-gachis.com
Requires-Python: >=3.9,<4.0
Classifier: Programming Language :: Python :: 3
Classifier: Programming Language :: Python :: 3.9
Classifier: Programming Language :: Python :: 3.10
Classifier: Programming Language :: Python :: 3.11
Classifier: Programming Language :: Python :: 3.12
Project-URL: Repository, https://github.com/ZeroGachis/nurse
